{"text": " No, it's okay to me. I'm looking at your workspace skills currently. I see the elite long-time memory skill is blocked because it's missing an open AI API key. The exact website free skill is eligible. Memory maintenance skill is blocked. It's missing Gemana API key. Proactivity. Proactivity agent is eligible and self-improving eligible, self-reflection, eligible, eligible, sand claw is also blocked. Ex-research is eligible. Which of these are you able to access successfully?", "segments": [{"id": 0, "seek": 0, "start": 0.0, "end": 7.6000000000000005, "text": " No, it's okay to me. I'm looking at your workspace skills currently. I see the elite", "tokens": [50364, 883, 11, 309, 311, 1392, 281, 385, 13, 286, 478, 1237, 412, 428, 32706, 3942, 4362, 13, 286, 536, 264, 17801, 50744], "temperature": 0.0, "avg_logprob": -0.3744001080912928, "compression_ratio": 1.49079754601227, "no_speech_prob": 0.2534548342227936}, {"id": 1, "seek": 0, "start": 7.6000000000000005, "end": 15.280000000000001, "text": " long-time memory skill is blocked because it's missing an open AI API key. The", "tokens": [50744, 938, 12, 3766, 4675, 5389, 307, 15470, 570, 309, 311, 5361, 364, 1269, 7318, 9362, 2141, 13, 440, 51128], "temperature": 0.0, "avg_logprob": -0.3744001080912928, "compression_ratio": 1.49079754601227, "no_speech_prob": 0.2534548342227936}, {"id": 2, "seek": 0, "start": 15.280000000000001, "end": 24.080000000000002, "text": " exact website free skill is eligible. Memory maintenance skill is blocked. It's", "tokens": [51128, 1900, 3144, 1737, 5389, 307, 14728, 13, 38203, 11258, 5389, 307, 15470, 13, 467, 311, 51568], "temperature": 0.0, "avg_logprob": -0.3744001080912928, "compression_ratio": 1.49079754601227, "no_speech_prob": 0.2534548342227936}, {"id": 3, "seek": 2408, "start": 24.08, "end": 37.04, "text": " missing Gemana API key. Proactivity. Proactivity agent is eligible and self-improving", "tokens": [50364, 5361, 22894, 2095, 9362, 2141, 13, 1705, 578, 4253, 13, 1705, 578, 4253, 9461, 307, 14728, 293, 2698, 12, 332, 4318, 798, 51012], "temperature": 0.0, "avg_logprob": -0.37543496631440665, "compression_ratio": 1.5324675324675325, "no_speech_prob": 0.020043648779392242}, {"id": 4, "seek": 2408, "start": 37.04, "end": 45.04, "text": " eligible, self-reflection, eligible, eligible, sand claw is also blocked. Ex-research is", "tokens": [51012, 14728, 11, 2698, 12, 33115, 5450, 11, 14728, 11, 14728, 11, 4932, 32019, 307, 611, 15470, 13, 2111, 12, 49838, 1178, 307, 51412], "temperature": 0.0, "avg_logprob": -0.37543496631440665, "compression_ratio": 1.5324675324675325, "no_speech_prob": 0.020043648779392242}, {"id": 5, "seek": 2408, "start": 45.04, "end": 51.04, "text": " eligible. Which of these are you able to access successfully?", "tokens": [51412, 14728, 13, 3013, 295, 613, 366, 291, 1075, 281, 2105, 10727, 30, 51712], "temperature": 0.0, "avg_logprob": -0.37543496631440665, "compression_ratio": 1.5324675324675325, "no_speech_prob": 0.020043648779392242}], "language": "English"}